donut/__init__.py
donut/_version.py
donut/model.py
donut/util.py
donut_python-1.0.8.dist-info/LICENSE
donut_python-1.0.8.dist-info/METADATA
donut_python-1.0.8.dist-info/NOTICE
donut_python-1.0.8.dist-info/WHEEL
donut_python-1.0.8.dist-info/top_level.txt
donut_python-1.0.8.dist-info/RECORD
