Metadata-Version: 2.1
Name: donut-python
Version: 1.0.8
Summary: OCR-free Document Understanding Transformer
Home-page: https://github.com/clovaai/donut
Author: Geewook Kim, Teakgyu Hong, Moonbin Yim, JeongYeon Nam, Jinyoung Park, Jinyeong Yim, Wonseok Hwang, Sangdoo Yun, Dongyoon Han, Seunghyun Park
Author-email: gwkim.rsrch@gmail.com
License: MIT
Platform: UNKNOWN
Classifier: Intended Audience :: Developers
Classifier: Intended Audience :: Information Technology
Classifier: Intended Audience :: Science/Research
Classifier: License :: OSI Approved :: MIT License
Classifier: Programming Language :: Python
Classifier: Programming Language :: Python :: 3
Classifier: Programming Language :: Python :: 3.7
Classifier: Programming Language :: Python :: 3.8
Classifier: Programming Language :: Python :: 3.9
Classifier: Programming Language :: Python :: 3.10
Classifier: Topic :: Scientific/Engineering :: Artificial Intelligence
Classifier: Topic :: Software Development :: Libraries
Classifier: Topic :: Software Development :: Libraries :: Python Modules
Requires-Python: >=3.7
Requires-Dist: transformers (>=4.11.3)
Requires-Dist: timm
Requires-Dist: datasets[vision]
Requires-Dist: pytorch-lightning (>=1.6.4)
Requires-Dist: nltk
Requires-Dist: sentencepiece
Requires-Dist: zss
Requires-Dist: sconf (>=0.2.3)
